frankenfit/__init__.py
frankenfit/backend.py
frankenfit/core.py
frankenfit/dataframe.py
frankenfit/mypy.py
frankenfit/params.py
frankenfit/py.typed
frankenfit/timeseries.py
frankenfit/universal.py
frankenfit-0.0.8.dist-info/LICENSE.txt
frankenfit-0.0.8.dist-info/METADATA
frankenfit-0.0.8.dist-info/WHEEL
frankenfit-0.0.8.dist-info/top_level.txt
frankenfit-0.0.8.dist-info/RECORD
