Metadata-Version: 2.1
Name: frankenfit
Version: 0.0.8
Summary: A Python library for creating, fitting, and applying predictive data modeling pipelines.
Author-email: Max Bane <max@thebanes.org>
Project-URL: Homepage, https://github.com/maxbane/frankenfit
Project-URL: Documentation, https://maxbane.github.io/frankenfit/current
Classifier: License :: OSI Approved :: BSD License
Classifier: Environment :: Console
Classifier: Operating System :: OS Independent
Classifier: Intended Audience :: Science/Research
Classifier: Intended Audience :: Developers
Classifier: Programming Language :: Python
Classifier: Programming Language :: Python :: 3 :: Only
Classifier: Programming Language :: Python :: 3.8
Classifier: Programming Language :: Python :: 3.9
Classifier: Programming Language :: Python :: 3.10
Classifier: Topic :: Scientific/Engineering
Classifier: Topic :: Software Development :: Libraries :: Python Modules
Classifier: Typing :: Typed
Requires-Python: >=3.8
License-File: LICENSE.txt
Requires-Dist: attrs
Requires-Dist: pandas
Requires-Dist: pyarrow
Requires-Dist: graphviz
Provides-Extra: dask
Requires-Dist: distributed ; extra == 'dask'
Provides-Extra: dev
Requires-Dist: frankenfit[dask,docs,tests] ; extra == 'dev'
Requires-Dist: pre-commit ; extra == 'dev'
Requires-Dist: build ; extra == 'dev'
Requires-Dist: tox (<4) ; extra == 'dev'
Requires-Dist: flake8 ; extra == 'dev'
Requires-Dist: flake8-pyproject ; extra == 'dev'
Requires-Dist: black ; extra == 'dev'
Requires-Dist: isort ; extra == 'dev'
Provides-Extra: docs
Requires-Dist: jupyter-server (<2) ; extra == 'docs'
Requires-Dist: jupyter-book (~=0.13) ; extra == 'docs'
Requires-Dist: furo ; extra == 'docs'
Requires-Dist: jupytext ; extra == 'docs'
Requires-Dist: pydataset ; extra == 'docs'
Requires-Dist: scikit-learn ; extra == 'docs'
Requires-Dist: matplotlib (~=3.6) ; extra == 'docs'
Requires-Dist: distributed ; extra == 'docs'
Provides-Extra: tests
Requires-Dist: frankenfit[dask] ; extra == 'tests'
Requires-Dist: pytest ; extra == 'tests'
Requires-Dist: pytest-xdist ; extra == 'tests'
Requires-Dist: pytest-cov ; extra == 'tests'
Requires-Dist: pydataset (==0.2.0) ; extra == 'tests'
Requires-Dist: scikit-learn ; extra == 'tests'
Requires-Dist: statsmodels ; extra == 'tests'
Requires-Dist: mypy (==0.991) ; extra == 'tests'
Requires-Dist: pandas-stubs (==1.5.1.221024) ; extra == 'tests'
